<?xml version="1.0" encoding="UTF-8"?>
<faces-config
    xmlns="http://xmlns.jcp.org/xml/ns/javaee"
    xmlns:xsi="http://www.w3.org/2001/XMLSchema-instance"
    xsi:schemaLocation="http://xmlns.jcp.org/xml/ns/javaee http://xmlns.jcp.org/xml/ns/javaee/web-facesconfig_2_2.xsd"
    version="2.2">
	<managed-bean>
		<managed-bean-name>cardData</managed-bean-name>
		<managed-bean-class>de.vogella.jsf.card.controller.CardController</managed-bean-class>
		<managed-bean-scope>session</managed-bean-scope>
		<managed-property>
			<property-name>card</property-name>
			<property-class>de.vogella.jsf.card.model.Card</property-class>
			<value>#{card}</value>
		</managed-property>
	</managed-bean>

</faces-config>
